app/README.md
app/__init__.py
app/cert.pem
app/key.pem
app/logger.py
app/models.py
app/router.py
app/server.py
app/vnc_server.py
app/__pycache__/__init__.cpython-312.pyc
app/__pycache__/logger.cpython-312.pyc
app/__pycache__/models.cpython-312.pyc
app/__pycache__/router.cpython-312.pyc
app/__pycache__/server.cpython-312.pyc
app/__pycache__/terminal_socket_server.cpython-312.pyc
app/__pycache__/vnc_server.cpython-312.pyc
app/helpers/__init__.py
app/helpers/tool_helpers.py
app/helpers/__pycache__/__init__.cpython-312.pyc
app/helpers/__pycache__/tool_helpers.cpython-312.pyc
app/helpers/__pycache__/utils.cpython-312.pyc
app/tools/base.py
app/tools/editor.py
app/tools/file.py
app/tools/zip.py
app/tools/__pycache__/__init__.cpython-312.pyc
app/tools/__pycache__/base.cpython-312.pyc
app/tools/__pycache__/editor.cpython-312.pyc
app/tools/__pycache__/file.cpython-312.pyc
app/tools/__pycache__/system_process.cpython-312.pyc
app/tools/__pycache__/text_editor.cpython-312.pyc
app/tools/__pycache__/zip.cpython-312.pyc
app/tools/browser/__init__.py
app/tools/browser/browser_actions.py
app/tools/browser/browser_helpers.py
app/tools/browser/browser_manager.py
app/tools/browser/__pycache__/__init__.cpython-312.pyc
app/tools/browser/__pycache__/browser_manager.cpython-312.pyc
app/tools/system/system_vnc.py
app/tools/system/__pycache__/system_vnc.cpython-312.pyc
app/tools/terminal/expecter.py
app/tools/terminal/terminal_helpers.py
app/tools/terminal/terminal_manager.py
app/tools/terminal/terminal_socket.py
app/tools/terminal/__pycache__/__init__.cpython-312.pyc
app/tools/terminal/__pycache__/expecter.cpython-312.pyc
app/tools/terminal/__pycache__/terminal_helpers.cpython-312.pyc
app/tools/terminal/__pycache__/terminal_manager.cpython-312.pyc
app/tools/terminal/__pycache__/terminal_socket.cpython-312.pyc
app/types/__init__.py
app/types/browser_types.py
app/types/messages.py
app/types/__pycache__/__init__.cpython-312.pyc
app/types/__pycache__/browser_types.cpython-312.pyc
orion_browser-0.6.0.dist-info/METADATA
orion_browser-0.6.0.dist-info/WHEEL
orion_browser-0.6.0.dist-info/entry_points.txt
orion_browser-0.6.0.dist-info/top_level.txt
orion_browser-0.6.0.dist-info/RECORD
